flask_timeloop/__init__.py
flask_timeloop/app.py
flask_timeloop/exceptions.py
flask_timeloop/helpers.py
flask_timeloop/job.py
flask_timeloop-0.2.4.dist-info/LICENSE
flask_timeloop-0.2.4.dist-info/WHEEL
flask_timeloop-0.2.4.dist-info/METADATA
flask_timeloop-0.2.4.dist-info/RECORD
