Metadata-Version: 2.1
Name: flask-timeloop
Version: 0.2.4
Summary: Timeloop module that integrates with Flask
License: MIT
Author: Taavi Ansper
Author-email: taavi.ansperr@gmail.com
Requires-Python: >=3.10,<4.0
Classifier: License :: OSI Approved :: MIT License
Classifier: Programming Language :: Python :: 3
Classifier: Programming Language :: Python :: 3.10
